telemetry_sdk/__init__.py
telemetry_sdk/client/__init__.py
telemetry_sdk/client/batch_manager.py
telemetry_sdk/client/event_builder.py
telemetry_sdk/client/models.py
telemetry_sdk/client/observation_span.py
telemetry_sdk/client/pricing.py
telemetry_sdk/client/telemetry_client.py
telemetry_sdk/client/trace_context.py
telemetry_sdk/instrumentation/__init__.py
telemetry_sdk/instrumentation/auto_instrumentation.py
telemetry_sdk/instrumentation/framework_integrations.py
telemetry_sdk/logging_integrations/__init__.py
telemetry_sdk/logging_integrations/handler.py
telemetry_sdk/logging_integrations/logger.py
telemetry_sdk/utils/__init__.py
telemetry_sdk/utils/config.py
telemetry_sdk/utils/exceptions.py
robotforge_python_sdk-0.2.3.dist-info/METADATA
robotforge_python_sdk-0.2.3.dist-info/WHEEL
robotforge_python_sdk-0.2.3.dist-info/entry_points.txt
robotforge_python_sdk-0.2.3.dist-info/top_level.txt
robotforge_python_sdk-0.2.3.dist-info/RECORD
